project/m2/rtl/compute_core.sv
// ==============================================================================
// Module: compute_core
// Description: INT8 Multiply-Accumulate (MAC) Processing Element for CNN 
//              spatial feature extraction.
//
// Clock Domain: Single clock domain (clk). No clock crossings exist.
// Reset: Synchronous, active-high reset (rst).
//
// Ports:
//  - clk        : input  : 1-bit  : System clock.
//  - rst        : input  : 1-bit  : Synchronous active-high reset.
//  - weight     : input  : 8-bit  : Signed INT8 weight from the CNN filter.
//  - feature_in : input  : 8-bit  : Signed INT8 RSSI feature sample.
//  - valid_in   : input  : 1-bit  : Control signal; high when inputs are valid.
//  - acc_out    : output : 32-bit : Signed 32-bit accumulated partial sum.
// ==============================================================================

module compute_core #(
    parameter DATA_WIDTH = 8,
    parameter ACC_WIDTH = 32
)(
    input  logic clk,
    input  logic rst,
    input  logic signed [DATA_WIDTH-1:0] weight,
    input  logic signed [DATA_WIDTH-1:0] feature_in,
    input  logic valid_in,
    output logic signed [ACC_WIDTH-1:0] acc_out
);

    // Internal pipeline registers
    logic signed [DATA_WIDTH*2-1:0] product;

    // Synchronous MAC logic
    always_ff @(posedge clk) begin
        if (rst) begin
            product <= '0;
            acc_out <= '0;
        end else if (valid_in) begin
            // Stage 1: Multiply RSSI by CNN weight
            product <= weight * feature_in;
            // Stage 2: Accumulate into the 32-bit register
            acc_out <= acc_out + product;
        end
    end

endmodule

project/m2/tb/tb_compute_core.sv
`timescale 1ns/1ps

module tb_compute_core();
    // Testbench signals
    logic clk;
    logic rst;
    logic signed [7:0] weight;
    logic signed [7:0] feature_in;
    logic valid_in;
    logic signed [31:0] acc_out;

    // Instantiate the Compute Core (DUT)
    compute_core #(.DATA_WIDTH(8), .ACC_WIDTH(32)) dut (
        .clk(clk),
        .rst(rst),
        .weight(weight),
        .feature_in(feature_in),
        .valid_in(valid_in),
        .acc_out(acc_out)
    );

    // Clock generation (10ns period)
    initial begin
        clk = 0;
        forever #5 clk = ~clk;
    end

    // Simulation sequence
    initial begin
        $dumpfile("sim/dump.vcd");
        $dumpvars(0, tb_compute_core);

        // 1. Apply Reset
        rst = 1;
        valid_in = 0;
        weight = 8'sd0;
        feature_in = 8'sd0;
        #20;
        rst = 0;
        #10;

        // 2. Input 1: Weight = 10, RSSI = -5 (product: -50)
        valid_in = 1;
        weight = 8'sd10;
        feature_in = -8'sd5;
        #10; 
        
        // 3. Input 2: Weight = 20, RSSI = 3 (product: 60)
        weight = 8'sd20;
        feature_in = 8'sd3;
        #10;

        // -> NEW: Flush the pipeline (1 extra cycle for the last addition)
        weight = 8'sd0;
        feature_in = 8'sd0;
        #10;
        
        valid_in = 0; // Stop pipeline
        #10;

        // 4. Independent Reference Check
        if (acc_out === 32'sd10) begin
            $display("========================================");
            $display("PASS: Compute core matched expected output (10).");
            $display("========================================");
        end else begin
            $display("FAIL: Expected 10, got %d", acc_out);
        end

        #20 $finish;
    end
endmodule

project/m2/sim/dump.vcd
$date
	Sun May  3 16:02:47 2026
$end
$version
	Icarus Verilog
$end
$timescale
	1ps
$end
$scope module tb_compute_core $end
$var wire 32 ! acc_out [31:0] $end
$var reg 1 " clk $end
$var reg 8 # feature_in [7:0] $end
$var reg 1 $ rst $end
$var reg 1 % valid_in $end
$var reg 8 & weight [7:0] $end
$scope module dut $end
$var wire 1 " clk $end
$var wire 8 ' feature_in [7:0] $end
$var wire 1 $ rst $end
$var wire 1 % valid_in $end
$var wire 8 ( weight [7:0] $end
$var parameter 32 ) ACC_WIDTH $end
$var parameter 32 * DATA_WIDTH $end
$var reg 32 + acc_out [31:0] $end
$var reg 16 , product [15:0] $end
$upscope $end
$upscope $end
$enddefinitions $end
$comment Show the parameter values. $end
$dumpall
b1000 *
b100000 )
$end
#0
$dumpvars
bx ,
bx +
b0 (
b0 '
b0 &
0%
1$
b0 #
0"
bx !
$end
#5000
b0 !
b0 +
b0 ,
1"
#10000
0"
#15000
1"
#20000
0"
0$
#25000
1"
#30000
0"
b11111011 #
b11111011 '
b1010 &
b1010 (
1%
#35000
b1111111111001110 ,
1"
#40000
0"
b11 #
b11 '
b10100 &
b10100 (
#45000
b11111111111111111111111111001110 !
b11111111111111111111111111001110 +
b111100 ,
1"
#50000
0"
b0 #
b0 '
b0 &
b0 (
#55000
b1010 !
b1010 +
b0 ,
1"
#60000
0"
0%
