project/m2/rtl/compute_core.sv
// ==============================================================================
// Module: compute_core
// Description: INT8 Multiply-Accumulate (MAC) Processing Element for CNN 
//              spatial feature extraction.
//
// Clock Domain: Single clock domain (clk). No clock crossings exist.
// Reset: Synchronous, active-high reset (rst).
//
// Ports:
//  - clk        : input  : 1-bit  : System clock.
//  - rst        : input  : 1-bit  : Synchronous active-high reset.
//  - weight     : input  : 8-bit  : Signed INT8 weight from the CNN filter.
//  - feature_in : input  : 8-bit  : Signed INT8 RSSI feature sample.
//  - valid_in   : input  : 1-bit  : Control signal; high when inputs are valid.
//  - acc_out    : output : 32-bit : Signed 32-bit accumulated partial sum.
// ==============================================================================

module compute_core #(
    parameter DATA_WIDTH = 8,
    parameter ACC_WIDTH = 32
)(
    input  logic clk,
    input  logic rst,
    input  logic signed [DATA_WIDTH-1:0] weight,
    input  logic signed [DATA_WIDTH-1:0] feature_in,
    input  logic valid_in,
    output logic signed [ACC_WIDTH-1:0] acc_out
);

    // Internal pipeline registers
    logic signed [DATA_WIDTH*2-1:0] product;

    // Synchronous MAC logic
    always_ff @(posedge clk) begin
        if (rst) begin
            product <= '0;
            acc_out <= '0;
        end else if (valid_in) begin
            // Stage 1: Multiply RSSI by CNN weight
            product <= weight * feature_in;
            // Stage 2: Accumulate into the 32-bit register
            acc_out <= acc_out + product;
        end
    end

endmodule

project/m2/rtl/interface.sv
module axis_interface #(
    parameter DATA_WIDTH = 8,
    parameter ACC_WIDTH = 32
)(
    input  logic aclk,
    input  logic aresetn,
    input  logic [15:0] s_axis_tdata,
    input  logic s_axis_tvalid,
    output logic s_axis_tready,
    input  logic s_axis_tlast,
    output logic [ACC_WIDTH-1:0] m_axis_tdata,
    output logic m_axis_tvalid,
    input  logic m_axis_tready,
    output logic m_axis_tlast
);
    logic [ACC_WIDTH-1:0] core_acc_out;
    logic [1:0] valid_pipe;
    logic [1:0] last_pipe;

    assign s_axis_tready = m_axis_tready;

    compute_core #(
        .DATA_WIDTH(DATA_WIDTH),
        .ACC_WIDTH(ACC_WIDTH)
    ) core_inst (
        .clk(aclk),
        .rst(~aresetn),
        .weight(s_axis_tdata[15:8]),
        .feature_in(s_axis_tdata[7:0]),
        .valid_in(s_axis_tvalid && s_axis_tready),
        .acc_out(core_acc_out)
    );

    always_ff @(posedge aclk) begin
        if (!aresetn) begin
            valid_pipe <= 2'b00;
            last_pipe  <= 2'b00;
        end else if (m_axis_tready) begin
            valid_pipe <= {valid_pipe[0], s_axis_tvalid};
            last_pipe  <= {last_pipe[0], s_axis_tlast};
        end
    end

    assign m_axis_tdata  = core_acc_out;
    assign m_axis_tvalid = valid_pipe[1];
    assign m_axis_tlast  = last_pipe[1];
endmodule

project/m2/tb/tb_interface.sv
`timescale 1ns/1ps

module tb_interface();
    logic aclk = 0;
    logic aresetn = 0;
    logic [15:0] s_axis_tdata = 0;
    logic s_axis_tvalid = 0;
    logic s_axis_tready;
    logic s_axis_tlast = 0;
    logic [31:0] m_axis_tdata;
    logic m_axis_tvalid;
    logic m_axis_tready = 1;
    logic m_axis_tlast;

    axis_interface dut (.*);

    always #5 aclk = ~aclk;

    initial begin
        $dumpfile("sim/dump_interface.vcd");
        $dumpvars(0, tb_interface);
        
        aresetn = 0; #20;
        aresetn = 1; #10;

        s_axis_tvalid = 1; s_axis_tdata = 16'h0AFB; #10;
        s_axis_tdata = 16'h1403; s_axis_tlast = 1; #10;
        s_axis_tvalid = 0; s_axis_tlast = 0;

        wait(m_axis_tvalid == 1); #20;

        if (m_axis_tdata !== 0)
            $display("PASS: Interface AXI-Stream simulation successful!");
        else
            $display("FAIL: No data output");

        $finish;
    end
endmodule

project/m2/sim/dump_interface.vcd
$date
	Sun May 17 22:46:39 2026
$end
$version
	Icarus Verilog
$end
$timescale
	1ps
$end
$scope module tb_interface $end
$var wire 1 ! s_axis_tready $end
$var wire 1 " m_axis_tvalid $end
$var wire 1 # m_axis_tlast $end
$var wire 32 $ m_axis_tdata [31:0] $end
$var reg 1 % aclk $end
$var reg 1 & aresetn $end
$var reg 1 ' m_axis_tready $end
$var reg 16 ( s_axis_tdata [15:0] $end
$var reg 1 ) s_axis_tlast $end
$var reg 1 * s_axis_tvalid $end
$scope module dut $end
$var wire 1 % aclk $end
$var wire 1 & aresetn $end
$var wire 32 + m_axis_tdata [31:0] $end
$var wire 1 ' m_axis_tready $end
$var wire 16 , s_axis_tdata [15:0] $end
$var wire 1 ) s_axis_tlast $end
$var wire 1 ! s_axis_tready $end
$var wire 1 * s_axis_tvalid $end
$var wire 1 " m_axis_tvalid $end
$var wire 1 # m_axis_tlast $end
$var wire 32 - core_acc_out [31:0] $end
$var parameter 32 . ACC_WIDTH $end
$var parameter 32 / DATA_WIDTH $end
$var reg 2 0 last_pipe [1:0] $end
$var reg 2 1 valid_pipe [1:0] $end
$scope module core_inst $end
$var wire 1 % clk $end
$var wire 8 2 feature_in [7:0] $end
$var wire 1 3 rst $end
$var wire 1 4 valid_in $end
$var wire 8 5 weight [7:0] $end
$var parameter 32 6 ACC_WIDTH $end
$var parameter 32 7 DATA_WIDTH $end
$var reg 32 8 acc_out [31:0] $end
$var reg 16 9 product [15:0] $end
$upscope $end
$upscope $end
$upscope $end
$enddefinitions $end
$comment Show the parameter values. $end
$dumpall
b1000 7
b100000 6
b1000 /
b100000 .
$end
#0
$dumpvars
bx 9
bx 8
b0 5
04
13
b0 2
bx 1
bx 0
bx -
b0 ,
bx +
0*
0)
b0 (
1'
0&
0%
bx $
x#
x"
1!
$end
#5000
0#
0"
b0 $
b0 +
b0 -
b0 8
b0 9
b0 0
b0 1
1%
#10000
0%
#15000
1%
#20000
03
0%
1&
#25000
1%
#30000
b1010 5
b11111011 2
14
0%
b101011111011 (
b101011111011 ,
1*
#35000
b1 1
b1111111111001110 9
1%
#40000
b10100 5
b11 2
0%
1)
b1010000000011 (
b1010000000011 ,
#45000
1"
b11111111111111111111111111001110 $
b11111111111111111111111111001110 +
b11111111111111111111111111001110 -
b11111111111111111111111111001110 8
b111100 9
b1 0
b11 1
1%
#50000
04
0%
0)
0*
#55000
1#
b10 0
b10 1
1%
#60000
0%
#65000
0#
0"
b0 0
b0 1
1%
