project/m4/rtl/compute_core.sv
`timescale 1ns / 1ps

module compute_core (
    input  logic        aclk,
    input  logic        aresetn,
    
    // Data from Interface
    input  logic [7:0]  rssi_in,
    input  logic [7:0]  weight_in,
    input  logic        valid_in,
    output logic        core_ready,
    
    // AXI4-Stream Master Interface (Output back to host)
    output logic [31:0] psum_out,      // 32-bit verified accumulator output
    output logic        psum_valid,
    input  logic        m_axis_tready
);

    // 16-bit wire to hold the direct result of INT8 x INT8
    logic signed [15:0] mult_result;
    
    // 32-bit verified partial sum accumulator register
    logic signed [31:0] accumulator;

    // The MAC array is ready when the downstream output is ready
    assign core_ready = m_axis_tready;
    
    // INT8 Combinational Multiplication
    // Treating the RSSI signal and CNN weight as signed integers
    assign mult_result = $signed(rssi_in) * $signed(weight_in);

    always_ff @(posedge aclk) begin
        if (!aresetn) begin
            accumulator <= 32'b0;
            psum_valid  <= 1'b0;
        end else if (valid_in && core_ready) begin
            // Safely accumulate the 16-bit multiplication into the 32-bit bucket
            accumulator <= accumulator + $signed(mult_result);
            psum_valid  <= 1'b1;
        end else if (m_axis_tready) begin
            psum_valid  <= 1'b0;
        end
    end

    // Assign final running total to the output port
    assign psum_out = accumulator;

endmodule

project/m4/rtl/interface.sv
`timescale 1ns / 1ps

module interface_unit (
    input  logic        aclk,
    input  logic        aresetn,
    
    // AXI4-Stream Slave Interface (Input from host)
    input  logic [15:0] s_axis_tdata,  // Upper 8 bits = RSSI, Lower 8 bits = Weight
    input  logic        s_axis_tvalid,
    output logic        s_axis_tready,
    
    // Handshake to Compute Core
    output logic [7:0]  rssi_out,
    output logic [7:0]  weight_out,
    output logic        valid_out,
    input  logic        core_ready
);

    // Pipeline register to prevent the setup violations seen in M3
    logic [15:0] tdata_reg;
    logic        tvalid_reg;

    // Always ready to accept data if the core is ready
    assign s_axis_tready = core_ready;

    always_ff @(posedge aclk) begin
        if (!aresetn) begin
            tdata_reg  <= 16'b0;
            tvalid_reg <= 1'b0;
        end else if (s_axis_tvalid && s_axis_tready) begin
            tdata_reg  <= s_axis_tdata;
            tvalid_reg <= 1'b1;
        end else if (core_ready) begin
            tvalid_reg <= 1'b0; // Clear valid if core consumes it but no new data arrives
        end
    end

    // Route the pipelined INT8 data to the compute core
    assign rssi_out   = tdata_reg[15:8];
    assign weight_out = tdata_reg[7:0];
    assign valid_out  = tvalid_reg;

endmodule

project/m4/rtl/top.sv
`timescale 1ns / 1ps

module top (
    input  logic        aclk,
    input  logic        aresetn,
    
    // Top-Level AXI4-Stream Slave (Input)
    input  logic [15:0] s_axis_tdata,
    input  logic        s_axis_tvalid,
    output logic        s_axis_tready,
    
    // Top-Level AXI4-Stream Master (Output)
    output logic [31:0] m_axis_tdata,
    output logic        m_axis_tvalid,
    input  logic        m_axis_tready
);

    // Internal routing wires connecting interface to compute core
    logic [7:0] internal_rssi;
    logic [7:0] internal_weight;
    logic       internal_valid;
    logic       internal_ready;

    // Instantiate the AXI Interface
    interface_unit u_interface (
        .aclk          (aclk),
        .aresetn       (aresetn),
        .s_axis_tdata  (s_axis_tdata),
        .s_axis_tvalid (s_axis_tvalid),
        .s_axis_tready (s_axis_tready),
        .rssi_out      (internal_rssi),
        .weight_out    (internal_weight),
        .valid_out     (internal_valid),
        .core_ready    (internal_ready)
    );

    // Instantiate the Compute Core
    compute_core u_compute (
        .aclk          (aclk),
        .aresetn       (aresetn),
        .rssi_in       (internal_rssi),
        .weight_in     (internal_weight),
        .valid_in      (internal_valid),
        .core_ready    (internal_ready),
        .psum_out      (m_axis_tdata),
        .psum_valid    (m_axis_tvalid),
        .m_axis_tready (m_axis_tready)
    );

endmodule

project/m4/tb/tb_top.sv
`timescale 1ns / 1ps

module tb_top();

    // 12ns clock period (83.33 MHz)
    logic aclk;
    logic aresetn;
    
    // AXI4-Stream Slave Interface (Input)
    logic [15:0] s_axis_tdata;
    logic        s_axis_tvalid;
    logic        s_axis_tready;
    
    // AXI4-Stream Master Interface (Output)
    logic [31:0] m_axis_tdata;
    logic        m_axis_tvalid;
    logic        m_axis_tready;

    // Instantiate the Top Module
    top dut (
        .aclk(aclk),
        .aresetn(aresetn),
        .s_axis_tdata(s_axis_tdata),
        .s_axis_tvalid(s_axis_tvalid),
        .s_axis_tready(s_axis_tready),
        .m_axis_tdata(m_axis_tdata),
        .m_axis_tvalid(m_axis_tvalid),
        .m_axis_tready(m_axis_tready)
    );

    // Clock Generation
    initial begin
        aclk = 0;
        forever #6 aclk = ~aclk; 
    end

    // Test Sequence
    initial begin
        // Setup waveform dumping for GTKWave
        $dumpfile("project/m4/sim/waveform.vcd");
        $dumpvars(0, tb_top);

        // 1. Initialize and Reset
        aresetn = 0;
        s_axis_tvalid = 0;
        s_axis_tdata = 0;
        m_axis_tready = 1; // Always ready to receive output

        #24; // Wait two clock cycles
        @(negedge aclk);
        aresetn = 1;

        // 2. Stress Test: Feed Maximum INT8 Values (127 x 127)
        // Using negedge prevents simulator race conditions
        @(negedge aclk);
        s_axis_tdata  = {8'd127, 8'd127}; 
        s_axis_tvalid = 1;
        
        // 3. Feed a second set of values (2 x 3)
        @(negedge aclk);
        s_axis_tdata  = {8'd2, 8'd3};
        
        // 4. Stop sending data
        @(negedge aclk);
        s_axis_tvalid = 0;

        // Wait for the pipeline and accumulator to process
        #100;
        
        // 5. Verification Check
        // 127*127 + 2*3 = 16129 + 6 = 16135
        if (m_axis_tdata === 32'd16135) begin
            $display("========================================");
            $display("SIMULATION RESULT: PASS");
            $display("Expected 32-bit Accumulator Output: 16135");
            $display("Actual 32-bit Accumulator Output:   %0d", m_axis_tdata);
            $display("========================================");
        end else begin
            $display("========================================");
            $display("SIMULATION RESULT: FAIL");
            $display("Expected: 16135, Got: %0d", m_axis_tdata);
            $display("========================================");
        end

        $finish;
    end

endmodule

project/m4/sim/waveform.vcd
$date
	Thu Jun  4 14:19:24 2026
$end
$version
	Icarus Verilog
$end
$timescale
	1ps
$end
$scope module tb_top $end
$var wire 1 ! s_axis_tready $end
$var wire 1 " m_axis_tvalid $end
$var wire 32 # m_axis_tdata [31:0] $end
$var reg 1 $ aclk $end
$var reg 1 % aresetn $end
$var reg 1 & m_axis_tready $end
$var reg 16 ' s_axis_tdata [15:0] $end
$var reg 1 ( s_axis_tvalid $end
$scope module dut $end
$var wire 1 $ aclk $end
$var wire 1 % aresetn $end
$var wire 1 & m_axis_tready $end
$var wire 16 ) s_axis_tdata [15:0] $end
$var wire 1 ( s_axis_tvalid $end
$var wire 1 ! s_axis_tready $end
$var wire 1 " m_axis_tvalid $end
$var wire 32 * m_axis_tdata [31:0] $end
$var wire 8 + internal_weight [7:0] $end
$var wire 1 , internal_valid $end
$var wire 8 - internal_rssi [7:0] $end
$var wire 1 . internal_ready $end
$scope module u_compute $end
$var wire 1 $ aclk $end
$var wire 1 % aresetn $end
$var wire 1 . core_ready $end
$var wire 1 & m_axis_tready $end
$var wire 32 / psum_out [31:0] $end
$var wire 8 0 weight_in [7:0] $end
$var wire 1 , valid_in $end
$var wire 8 1 rssi_in [7:0] $end
$var wire 16 2 mult_result [15:0] $end
$var reg 32 3 accumulator [31:0] $end
$var reg 1 " psum_valid $end
$upscope $end
$scope module u_interface $end
$var wire 1 $ aclk $end
$var wire 1 % aresetn $end
$var wire 1 . core_ready $end
$var wire 16 4 s_axis_tdata [15:0] $end
$var wire 1 ! s_axis_tready $end
$var wire 1 ( s_axis_tvalid $end
$var wire 1 , valid_out $end
$var wire 8 5 weight_out [7:0] $end
$var wire 8 6 rssi_out [7:0] $end
$var reg 16 7 tdata_reg [15:0] $end
$var reg 1 8 tvalid_reg $end
$upscope $end
$upscope $end
$upscope $end
$enddefinitions $end
$comment Show the parameter values. $end
$dumpall
$end
#0
$dumpvars
x8
bx 7
bx 6
bx 5
b0 4
bx 3
bx 2
bx 1
bx 0
bx /
1.
bx -
x,
bx +
bx *
b0 )
0(
b0 '
1&
0%
0$
bx #
x"
1!
$end
#6000
b0 2
b0 -
b0 1
b0 6
b0 +
b0 0
b0 5
0,
08
b0 7
0"
b0 #
b0 *
b0 /
b0 3
1$
#12000
0$
#18000
1$
#24000
1%
0$
#30000
1$
#36000
1(
b111111101111111 '
b111111101111111 )
b111111101111111 4
0$
#42000
b11111100000001 2
b1111111 -
b1111111 1
b1111111 6
b1111111 +
b1111111 0
b1111111 5
1,
18
b111111101111111 7
1$
#48000
b1000000011 '
b1000000011 )
b1000000011 4
0$
#54000
b10 -
b10 1
b10 6
b110 2
b11 +
b11 0
b11 5
b1000000011 7
1"
b11111100000001 #
b11111100000001 *
b11111100000001 /
b11111100000001 3
1$
#60000
0(
0$
#66000
b11111100000111 #
b11111100000111 *
b11111100000111 /
b11111100000111 3
0,
08
1$
#72000
0$
#78000
0"
1$
