project/m2/rtl/compute_core.sv
// ==============================================================================
// Module: compute_core
// Description: INT8 Multiply-Accumulate (MAC) Processing Element for CNN 
//              spatial feature extraction.
//
// Clock Domain: Single clock domain (clk). No clock crossings exist.
// Reset: Synchronous, active-high reset (rst).
//
// Ports:
//  - clk        : input  : 1-bit  : System clock.
//  - rst        : input  : 1-bit  : Synchronous active-high reset.
//  - weight     : input  : 8-bit  : Signed INT8 weight from the CNN filter.
//  - feature_in : input  : 8-bit  : Signed INT8 RSSI feature sample.
//  - valid_in   : input  : 1-bit  : Control signal; high when inputs are valid.
//  - acc_out    : output : 32-bit : Signed 32-bit accumulated partial sum.
// ==============================================================================

module compute_core #(
    parameter DATA_WIDTH = 8,
    parameter ACC_WIDTH = 32
)(
    input  logic clk,
    input  logic rst,
    input  logic signed [DATA_WIDTH-1:0] weight,
    input  logic signed [DATA_WIDTH-1:0] feature_in,
    input  logic valid_in,
    output logic signed [ACC_WIDTH-1:0] acc_out
);

    // Internal pipeline registers
    logic signed [DATA_WIDTH*2-1:0] product;

    // Synchronous MAC logic
    always_ff @(posedge clk) begin
        if (rst) begin
            product <= '0;
            acc_out <= '0;
        end else if (valid_in) begin
            // Stage 1: Multiply RSSI by CNN weight
            product <= weight * feature_in;
            // Stage 2: Accumulate into the 32-bit register
            acc_out <= acc_out + product;
        end
    end

endmodule

project/m2/rtl/interface.sv
module axis_interface #(
    parameter DATA_WIDTH = 8,
    parameter ACC_WIDTH = 32
)(
    input  logic aclk,
    input  logic aresetn,
    input  logic [15:0] s_axis_tdata,
    input  logic s_axis_tvalid,
    output logic s_axis_tready,
    input  logic s_axis_tlast,
    output logic [ACC_WIDTH-1:0] m_axis_tdata,
    output logic m_axis_tvalid,
    input  logic m_axis_tready,
    output logic m_axis_tlast
);
    logic [ACC_WIDTH-1:0] core_acc_out;
    logic [1:0] valid_pipe;
    logic [1:0] last_pipe;

    assign s_axis_tready = m_axis_tready;

    compute_core #(
        .DATA_WIDTH(DATA_WIDTH),
        .ACC_WIDTH(ACC_WIDTH)
    ) core_inst (
        .clk(aclk),
        .rst(~aresetn),
        .weight(s_axis_tdata[15:8]),
        .feature_in(s_axis_tdata[7:0]),
        .valid_in(s_axis_tvalid && s_axis_tready),
        .acc_out(core_acc_out)
    );

    always_ff @(posedge aclk) begin
        if (!aresetn) begin
            valid_pipe <= 2'b00;
            last_pipe  <= 2'b00;
        end else if (m_axis_tready) begin
            valid_pipe <= {valid_pipe[0], s_axis_tvalid};
            last_pipe  <= {last_pipe[0], s_axis_tlast};
        end
    end

    assign m_axis_tdata  = core_acc_out;
    assign m_axis_tvalid = valid_pipe[1];
    assign m_axis_tlast  = last_pipe[1];
endmodule

project/m3/rtl/top.sv
`timescale 1ns / 1ps

/*
 * Module: top
 * Description: Integrated top-level module for the CNN MAC Hardware Accelerator.
 *
 * Port List Documentation (M3 Requirement):
 * -----------------------------------------------------------------------------
 * Name            | Direction | Width | Role
 * ----------------|-----------|-------|----------------------------------------
 * aclk            | input     | 1     | Master system clock.
 * aresetn         | input     | 1     | Active-low synchronous reset.
 * s_axis_tdata    | input     | 16    | AXI4-Stream slave data (INT8 features/weights).
 * s_axis_tvalid   | input     | 1     | AXI4-Stream slave valid signal.
 * s_axis_tready   | output    | 1     | AXI4-Stream slave ready signal.
 * s_axis_tlast    | input     | 1     | AXI4-Stream slave last signal.
 * m_axis_tdata    | output    | 32    | AXI4-Stream master data (INT32 MAC result).
 * m_axis_tvalid   | output    | 1     | AXI4-Stream master valid signal.
 * m_axis_tready   | input     | 1     | AXI4-Stream master ready signal.
 * m_axis_tlast    | output    | 1     | AXI4-Stream master last signal.
 * -----------------------------------------------------------------------------
 *
 * Glue Logic Identification (M3 Requirement):
 * None required.
 */

module top (
    input  wire         aclk,
    input  wire         aresetn,
    
    // AXI4-Stream Slave Interface (Updated to 16 bits to match M2 core)
    input  wire [15:0]  s_axis_tdata,
    input  wire         s_axis_tvalid,
    output wire         s_axis_tready,
    input  wire         s_axis_tlast,
    
    // AXI4-Stream Master Interface
    output wire [31:0]  m_axis_tdata,
    output wire         m_axis_tvalid,
    input  wire         m_axis_tready,
    output wire         m_axis_tlast
);

    axis_interface cnn_mac_wrapper (
        .aclk(aclk),
        .aresetn(aresetn),
        .s_axis_tdata(s_axis_tdata),
        .s_axis_tvalid(s_axis_tvalid),
        .s_axis_tready(s_axis_tready),
        .s_axis_tlast(s_axis_tlast),
        .m_axis_tdata(m_axis_tdata),
        .m_axis_tvalid(m_axis_tvalid),
        .m_axis_tready(m_axis_tready),
        .m_axis_tlast(m_axis_tlast)
    );

endmodule

project/m3/tb/tb_top.sv
`timescale 1ns / 1ps

module tb_top();

    // Clock and Reset
    reg         aclk;
    reg         aresetn;

    // AXI4-Stream Slave
    reg  [15:0] s_axis_tdata;
    reg         s_axis_tvalid;
    wire        s_axis_tready;
    reg         s_axis_tlast;

    // AXI4-Stream Master
    wire [31:0] m_axis_tdata;
    wire        m_axis_tvalid;
    reg         m_axis_tready;
    wire        m_axis_tlast;

    integer i;
    reg signed [7:0] features [0:8];
    reg signed [7:0] weights  [0:8];

    // Instantiate Top Module
    top dut (
        .aclk(aclk),
        .aresetn(aresetn),
        .s_axis_tdata(s_axis_tdata),
        .s_axis_tvalid(s_axis_tvalid),
        .s_axis_tready(s_axis_tready),
        .s_axis_tlast(s_axis_tlast),
        .m_axis_tdata(m_axis_tdata),
        .m_axis_tvalid(m_axis_tvalid),
        .m_axis_tready(m_axis_tready),
        .m_axis_tlast(m_axis_tlast)
    );

    // Clock Generation
    initial begin
        aclk = 0;
        forever #5 aclk = ~aclk;
    end

    // VCD Dumping
    initial begin
        $dumpfile("m3/sim/cosim.vcd");
        $dumpvars(0, tb_top);
    end

    // Test Stimulus
    initial begin
        // Manually load the array. 9th feature is 0 so expected sum is exactly -4
        features[0] = 1; features[1] = -2; features[2] = 3;
        features[3] = -4; features[4] = 5; features[5] = -6;
        features[6] = 7; features[7] = -8; features[8] = 0;

        weights[0] = 1; weights[1] = 1; weights[2] = 1;
        weights[3] = 1; weights[4] = 1; weights[5] = 1;
        weights[6] = 1; weights[7] = 1; weights[8] = 1;

        // Initialize signals
        aresetn = 0;
        s_axis_tdata = 0;
        s_axis_tvalid = 0;
        s_axis_tlast = 0;
        m_axis_tready = 1; 

        // Assert reset
        #20 aresetn = 1;
        #10;

        // --- HOST WRITE TRANSACTION ---
        for (i = 0; i < 9; i = i + 1) begin
            // Pack the data and assert valid
            s_axis_tdata = {features[i], weights[i]}; 
            s_axis_tvalid = 1;
            s_axis_tlast = (i == 8) ? 1'b1 : 1'b0;
            
            // Wait for the clock edge
            @(posedge aclk);
            
            // If core is not ready, hold the data until it is
            while (s_axis_tready == 0) begin
                @(posedge aclk);
            end
        end
        
        // Deassert signals after loop finishes
        s_axis_tvalid = 0;
        s_axis_tlast = 0;

        // --- HOST READ TRANSACTION & VERIFICATION ---
        wait(m_axis_tvalid == 1);
        @(posedge aclk);
        
        // Expected INT32 MAC Result: -4 (32'hfffffffc)
        if (m_axis_tdata == 32'hfffffffc) begin
            $display("========================================");
            $display("PASS");
            $display("========================================");
        end else begin
            $display("========================================");
            $display("FAIL: Expected fffffffc, Got %h", m_axis_tdata);
            $display("========================================");
        end

        #20 $finish;
    end
endmodule

project/m3/sim/cosim.vcd
$date
	Fri May 22 21:48:32 2026
$end
$version
	Icarus Verilog
$end
$timescale
	1ps
$end
$scope module tb_top $end
$var wire 1 ! s_axis_tready $end
$var wire 1 " m_axis_tvalid $end
$var wire 1 # m_axis_tlast $end
$var wire 32 $ m_axis_tdata [31:0] $end
$var reg 1 % aclk $end
$var reg 1 & aresetn $end
$var reg 1 ' m_axis_tready $end
$var reg 16 ( s_axis_tdata [15:0] $end
$var reg 1 ) s_axis_tlast $end
$var reg 1 * s_axis_tvalid $end
$var integer 32 + i [31:0] $end
$scope module dut $end
$var wire 1 % aclk $end
$var wire 1 & aresetn $end
$var wire 1 ' m_axis_tready $end
$var wire 16 , s_axis_tdata [15:0] $end
$var wire 1 ) s_axis_tlast $end
$var wire 1 * s_axis_tvalid $end
$var wire 1 ! s_axis_tready $end
$var wire 1 " m_axis_tvalid $end
$var wire 1 # m_axis_tlast $end
$var wire 32 - m_axis_tdata [31:0] $end
$scope module cnn_mac_wrapper $end
$var wire 1 % aclk $end
$var wire 1 & aresetn $end
$var wire 32 . m_axis_tdata [31:0] $end
$var wire 1 ' m_axis_tready $end
$var wire 16 / s_axis_tdata [15:0] $end
$var wire 1 ) s_axis_tlast $end
$var wire 1 ! s_axis_tready $end
$var wire 1 * s_axis_tvalid $end
$var wire 1 " m_axis_tvalid $end
$var wire 1 # m_axis_tlast $end
$var wire 32 0 core_acc_out [31:0] $end
$var parameter 32 1 ACC_WIDTH $end
$var parameter 32 2 DATA_WIDTH $end
$var reg 2 3 last_pipe [1:0] $end
$var reg 2 4 valid_pipe [1:0] $end
$scope module core_inst $end
$var wire 1 % clk $end
$var wire 8 5 feature_in [7:0] $end
$var wire 1 6 rst $end
$var wire 1 7 valid_in $end
$var wire 8 8 weight [7:0] $end
$var parameter 32 9 ACC_WIDTH $end
$var parameter 32 : DATA_WIDTH $end
$var reg 32 ; acc_out [31:0] $end
$var reg 16 < product [15:0] $end
$upscope $end
$upscope $end
$upscope $end
$upscope $end
$enddefinitions $end
$comment Show the parameter values. $end
$dumpall
b1000 :
b100000 9
b1000 2
b100000 1
$end
#0
$dumpvars
bx <
bx ;
b0 8
07
16
b0 5
bx 4
bx 3
bx 0
b0 /
bx .
bx -
b0 ,
bx +
0*
0)
b0 (
1'
0&
0%
bx $
x#
x"
1!
$end
#5000
0#
0"
b0 $
b0 -
b0 .
b0 0
b0 ;
b0 <
b0 3
b0 4
1%
#10000
0%
#15000
1%
#20000
06
0%
1&
#25000
1%
#30000
17
b1 8
b1 5
0%
1*
b100000001 (
b100000001 ,
b100000001 /
b0 +
#35000
b1 4
b1 <
b11111110 8
b1111111000000001 (
b1111111000000001 ,
b1111111000000001 /
b1 +
1%
#40000
0%
#45000
1"
b1 $
b1 -
b1 .
b1 0
b1 ;
b1111111111111110 <
b11 4
b11 8
b1100000001 (
b1100000001 ,
b1100000001 /
b10 +
1%
#50000
0%
#55000
b11111111111111111111111111111111 $
b11111111111111111111111111111111 -
b11111111111111111111111111111111 .
b11111111111111111111111111111111 0
b11111111111111111111111111111111 ;
b11 <
b11111100 8
b1111110000000001 (
b1111110000000001 ,
b1111110000000001 /
b11 +
1%
#60000
0%
#65000
b10 $
b10 -
b10 .
b10 0
b10 ;
b1111111111111100 <
b101 8
b10100000001 (
b10100000001 ,
b10100000001 /
b100 +
1%
#70000
0%
#75000
b11111111111111111111111111111110 $
b11111111111111111111111111111110 -
b11111111111111111111111111111110 .
b11111111111111111111111111111110 0
b11111111111111111111111111111110 ;
b101 <
b11111010 8
b1111101000000001 (
b1111101000000001 ,
b1111101000000001 /
b101 +
1%
#80000
0%
#85000
b11 $
b11 -
b11 .
b11 0
b11 ;
b1111111111111010 <
b111 8
b11100000001 (
b11100000001 ,
b11100000001 /
b110 +
1%
#90000
0%
#95000
b11111111111111111111111111111101 $
b11111111111111111111111111111101 -
b11111111111111111111111111111101 .
b11111111111111111111111111111101 0
b11111111111111111111111111111101 ;
b111 <
b11111000 8
b1111100000000001 (
b1111100000000001 ,
b1111100000000001 /
b111 +
1%
#100000
0%
#105000
b100 $
b100 -
b100 .
b100 0
b100 ;
b1111111111111000 <
b0 8
1)
b1 (
b1 ,
b1 /
b1000 +
1%
#110000
0%
#115000
b10 4
b11111111111111111111111111111100 $
b11111111111111111111111111111100 -
b11111111111111111111111111111100 .
b11111111111111111111111111111100 0
b11111111111111111111111111111100 ;
b0 <
07
0)
0*
b1001 +
1%
#120000
0%
#125000
0"
b0 4
1%
