codefest/cf04/cocotb_mac/mac_correct.v
module mac (
    input  logic clk,
    input  logic rst,
    input  logic signed [7:0] a,
    input  logic signed [7:0] b,
    output logic signed [31:0] out
);

    logic signed [31:0] prod;

    // Combinational logic for multiplication
    assign prod = a * b;

    // Sequential logic for accumulation
    always_ff @(posedge clk) begin
        if (rst) begin
            out <= 32'sd0;
        end else begin
            out <= out + prod;
        end
    end

    // --- COPT Verification Block ---
    // This allows cocotb to record signals for GTKWave
    initial begin
        $dumpfile("dump.vcd"); // Creates the wave file
        $dumpvars(0, mac);      // Dumps all signals in this module
    end

endmodule

codefest/cf04/cocotb_mac/dump.vcd
$date
	Sun Apr 26 22:16:12 2026
$end
$version
	Icarus Verilog
$end
$timescale
	1ps
$end
$scope module mac $end
$var wire 8 ! a [7:0] $end
$var wire 8 " b [7:0] $end
$var wire 1 # clk $end
$var wire 1 $ rst $end
$var wire 32 % prod [31:0] $end
$var reg 32 & out [31:0] $end
$upscope $end
$enddefinitions $end
$comment Show the parameter values. $end
$dumpall
$end
#0
$dumpvars
b0 &
b1100 %
0$
1#
b100 "
b11 !
$end
#5000
0#
#10000
b1100 &
1#
#15000
0#
#20000
b11000 &
1#
#25000
0#
#30000
b100100 &
1#
#31001
1$
#36001
0#
#41001
b1111111 "
b11111100000001 %
b1111111 !
0$
b0 &
1#
#46001
0#
#51001
b11111100000001 &
1#
#56001
0#
#61001
b111111000000010 &
1#
#66001
0#
#71001
b1011110100000011 &
1#
#76001
0#
#81001
b1111110000000100 &
1#
#86001
0#
#91001
b10011101100000101 &
1#
#96001
0#
#101001
b10111101000000110 &
1#
#106001
0#
#111001
b11011100100000111 &
1#
#116001
0#
#121001
b11111100000001000 &
1#
#126001
0#
#131001
b100011011100001001 &
1#
#136001
0#
#141001
b100111011000001010 &
1#
